{
  "target_min_tokens": 15000,
  "auto_fill_start_gap": 1,
  "check_interval_minutes": 1,
  "manual_default_threads": 20,
  "manual_register_retries": 3,
  "web_token": "linuxdo",
  "client_api_token": "linuxdo",
  "client_notice": "",
  "minimum_client_version": "",
  "enabled_email_domains": [
    "*.icoa.qzz.io",
    "*.icoe.pp.ua",
    "*.icoa.pp.ua",
    "*.uoou.cc.cd",
    "*.icoa.us.ci",
    "*.ice.qq11.top",
    "*.myanglealtman.tech",
    "*.ice.lyzswx.eu.org",
    "*.ice.aoko.cc.cd",
    "*.ice.aoko.eu.cc",
    "*.ice.chaldea.eu.cc",
    "*.ice.mssk.eu.cc",
    "*.ice.mssk.qzz.io",
    "*.linux.archerguo.de5.net",
    "*.linux.airforceone.online",
    "*.ice.kitakamis.online",
    "*.ice.0987134.xyz",
    "*.ice.icecodex.us.ci",
    "*.ice.oo.oogoo.top",
    "*.ice.jiayou0328.us.ci",
    "*.icecream.707979.xyz",
    "*.ice.help.itbasee.top",
    "*.ice.863973.dpdns.org",
    "*.ice.tinytiger.top",
    "*.ice.yucici.qzz.io",
    "*.love.biaozi.de5.net",
    "*.love.dogge.de5.net",
    "*.love.mobil.dpdns.org",
    "*.love.vercel.dpdns.org",
    "*.love.google.nyc.mn"
  ],
  "mail_domain_options": [
    "*.icoa.qzz.io",
    "*.icoe.pp.ua",
    "*.icoa.pp.ua",
    "*.uoou.cc.cd",
    "*.icoa.ccwu.cc",
    "*.icoa.us.ci",
    "*.ice.qq11.top",
    "*.myanglealtman.tech",
    "*.ice.lyzswx.eu.org",
    "*.ice.aoko.cc.cd",
    "*.ice.aoko.eu.cc",
    "*.ice.chaldea.eu.cc",
    "*.ice.mssk.eu.cc",
    "*.ice.mssk.qzz.io",
    "*.linux.archerguo.de5.net",
    "*.linux.airforceone.online",
    "*.ice.kitakamis.online",
    "*.ice.0987134.xyz",
    "*.ice.icecodex.us.ci",
    "*.ice.icecodex.ccwu.cc",
    "*.ice.oo.oogoo.top",
    "*.ice.jiayou0328.ccwu.cc",
    "*.ice.jiayou0328.us.ci",
    "*.icecream.707979.xyz",
    "*.ice.help.itbasee.top",
    "*.ice.863973.dpdns.org",
    "*.ice.tinytiger.top",
    "*.ice.yucici.qzz.io",
    "*.love.biaozi.de5.net",
    "*.love.dogge.de5.net",
    "*.love.mobil.dpdns.org",
    "*.love.vercel.dpdns.org",
    "*.love.google.nyc.mn"
  ],
  "default_proxy": "http://127.0.0.1:7897",
  "use_registration_proxy": false,
  "cpa_base_url": "http://localhost:8317/",
  "cpa_token": "7403",
  "mail_api_url": "https://gpt-mail.icoa.pp.ua/",
  "mail_api_key": "linuxdo",
  "port": 25666
}
